rtl/PRNG/PRNG.v
module PRNG #( parameter DATA_WIDTH = 32, NUMBER_RANDOM = 2) (
	input clk,
	input rst_n,
	input start,
	input re_start,
	output wire out_valid,
	output reg [31:0] data_out,
	output reg end_random,
	output reg [31:0] number_1,
	output reg [31:0] number_2
);

	parameter N = 624          ;
	parameter M = 397          ;
	parameter R = 31           ;
	parameter A = 32'h9908B0DF ;
	parameter U = 11           ;
	parameter D = 32'hFFFFFFFF ;
	parameter S = 7            ;
	parameter B = 32'h9D2C5680 ;
	parameter T = 15           ;
	parameter C = 32'hEFC60000 ;
	parameter L = 18           ;
	parameter F = 1812433253   ;
	parameter SEED = 32'h87878787; 
	parameter W = 32; 

	parameter [2:0] IDLE          = 3'b000;
	parameter [2:0] INIT          = 3'b001;
	parameter [2:0] TRANFORMATION = 3'b010;
	parameter [2:0] TEMPERING     = 3'b011;
	parameter [2:0] END_RANDOM    = 3'b100;

	reg [2:0] current_state, next_state;
	reg [10:0] counter_init;
	reg [10:0] counter_tran;
	reg [10:0] counter_temp;
	wire [W-1:0] upper_mask;
	wire [W-1:0] lower_mask;
	reg [31:0] y;
	reg [31:0] x;
	reg [31:0] x1;
	reg [31:0] out_tranformation;

	//reg [5:0] i;

	reg [31:0] y1,y2,y3,y4,y5,y6,y7,y8,y9,y10;
	assign lower_mask = (1 << R) - 1;
	assign upper_mask = ~lower_mask & {W{1'b1}};
	always @(posedge clk or negedge rst_n) begin
		if(!rst_n) begin
			current_state <= IDLE;
	  end else begin
			current_state <= next_state;
		end
	end

	always @(*) begin
		case(current_state)
			IDLE: begin
				if(start) begin 
					next_state = INIT;
				end else begin
					next_state = IDLE;
				end
			end
			INIT: begin 
				if(counter_init == N) begin 
					next_state = TRANFORMATION;
				end else begin
					next_state = INIT;
				end
			end
			TRANFORMATION: begin
				if (counter_tran == N) begin
					next_state = TEMPERING;
				end else begin
					next_state = TRANFORMATION;
				end
			end
			TEMPERING: begin
				if(counter_temp == 32) begin
					next_state = END_RANDOM;
				end else begin
					next_state = TEMPERING;
				end
			end
			END_RANDOM: begin
				if(re_start) begin 
					next_state = TRANFORMATION;
				end else begin
					next_state = END_RANDOM;
				end
			end
			default: next_state = IDLE;
			endcase
	end
	reg [31:0] state_vector [623:0] ;
	wire [31:0] temp;
	assign temp = state_vector[counter_init] ^ (state_vector[counter_init] >> (W-2));
  integer i;
	always @(posedge clk or negedge rst_n) begin
		if(!rst_n) begin
			counter_init <= 0;
			counter_tran <= 0;
			counter_temp <= 0;
			out_tranformation <= 0;
			y   <= 0;
			y1  <= 0;
			y2  <= 0;
			y3  <= 0;
			y4  <= 0;
			y5  <= 0;
			y6  <= 0;
			y7  <= 0;
			y8  <= 0;
			y9  <= 0;
			y10 <= 0;
			x1  <= 0;
			x   <= 0;
			for (i = 0; i < N; i = i + 1) begin
				state_vector[i] <= 0;
			end
		end else begin
			case(next_state)
				IDLE: begin 
					state_vector[0] <= SEED;
				end 
				INIT: begin
					counter_init <= counter_init + 1;
					state_vector[counter_init+1] <= (F * (state_vector[counter_init] ^ (state_vector[counter_init] >> (W-2))) + counter_init) & 32'hFFFFFFFF;
				end
				TRANFORMATION: begin 
					counter_tran <= counter_tran + 1; 
					y <= (state_vector[counter_tran] & upper_mask) + (state_vector[(counter_tran + 1 ) % N] & lower_mask);
					x <= y >> 1;
					if(x[0] == 1) begin
						x1 <= x ^ A;
						state_vector[counter_tran] <= state_vector[((counter_tran + M) % N)] ^ x1;					
					  out_tranformation	 <= state_vector[((counter_tran + M) % N)] ^ x1;					
					end else begin
						state_vector[counter_tran] <= state_vector[((counter_tran + M) % N)] ^ x;					
					  out_tranformation	 <= state_vector[((counter_tran + M) % N)] ^ x;					
						//counter_tran <= 0;
					end
				end
				TEMPERING: begin
					counter_temp <= counter_temp + 1; 
					y1  <= (out_tranformation >> U) ;
					y2  <= out_tranformation ^ y1   ;
					y3  <=  y2 << S                 ;
					y4  <=  y3 & C                  ;
					y5  <=  y4 ^ y2                 ;
					y6  <=  y5 << 15                ;
					y7  <=  y6 & C                  ;
					y8  <=  y7 ^ y5                 ;
					y9  <=  y8 >> L                 ;
					y10 <=  y9 ^ y8                 ;
				end
				END_RANDOM: begin 
					counter_tran <= 0;
					counter_temp <= 0;
				end
			endcase
		end
	end
	wire test;
	assign test = ((counter_temp == 6) | (counter_temp == 7));

	assign out_valid = (counter_temp == 5) ? 1 : 0;

endmodule

rtl/PRNG/tb.v
module tb ();
	reg clk, rst_n;
	reg start;
	reg re_start;
	wire out_valid;
	wire [31:0] data_out;
	wire end_random;


PRNG #(.DATA_WIDTH(32)) dut (
	.clk(clk),
	.rst_n(rst_n),
	.start(start),
	.re_start(re_start),
	.out_valid(out_valid),
	.data_out(data_out),
	.end_random(end_random)
);

initial begin
	$dumpfile("PRNG.VCD");
	$dumpvars(0,tb);
end
integer i;
reg [31:0] state [623:0];
//always @(posedge out_valid ) begin
//	for(i = 0; i < 624 ; i = i+ 1) begin
//		state[i] = dut.state_vector[i];
//		$display(" state vector %d: %h ", i, state[i]);
//	end
//end	

always #5 clk = !clk;
initial begin
	#0 rst_n  = 1;
			clk   = 0;
	re_start = 0;
	#10 rst_n = 0;
	#10 rst_n = 1;
	#40 start = 1;
	#20 start = 0;
	#13500 re_start = 1;
	#20 re_start = 0;

end
initial begin
	#100000 $finish;
end
always @(posedge out_valid) begin
	if(out_valid) begin
		$display("the random number generated in the range [0:1] is %f" , (dut.y10)/($itor(32'hFFFFFFFF)));
	end
end
endmodule

rtl/PRNG/PRNG.VCD
$date
	Thu Jan 30 19:13:33 2025
$end
$version
	Icarus Verilog
$end
$timescale
	1s
$end
$scope module tb $end
$var wire 1 ! out_valid $end
$var wire 1 " end_random $end
$var wire 32 # data_out [31:0] $end
$var reg 1 $ clk $end
$var reg 1 % re_start $end
$var reg 1 & rst_n $end
$var reg 1 ' start $end
$scope module dut $end
$var wire 1 $ clk $end
$var wire 32 ( lower_mask [31:0] $end
$var wire 1 % re_start $end
$var wire 1 & rst_n $end
$var wire 1 ' start $end
$var wire 32 ) temp [31:0] $end
$var wire 1 * test $end
$var wire 32 + upper_mask [31:0] $end
$var wire 1 ! out_valid $end
$var reg 11 , counter_init [10:0] $end
$var reg 11 - counter_temp [10:0] $end
$var reg 11 . counter_tran [10:0] $end
$var reg 3 / current_state [2:0] $end
$var reg 32 0 data_out [31:0] $end
$var reg 1 " end_random $end
$var reg 3 1 next_state [2:0] $end
$var reg 32 2 number_1 [31:0] $end
$var reg 32 3 number_2 [31:0] $end
$var reg 32 4 out_tranformation [31:0] $end
$var reg 32 5 x [31:0] $end
$var reg 32 6 x1 [31:0] $end
$var reg 32 7 y [31:0] $end
$var reg 32 8 y1 [31:0] $end
$var reg 32 9 y10 [31:0] $end
$var reg 32 : y2 [31:0] $end
$var reg 32 ; y3 [31:0] $end
$var reg 32 < y4 [31:0] $end
$var reg 32 = y5 [31:0] $end
$var reg 32 > y6 [31:0] $end
$var reg 32 ? y7 [31:0] $end
$var reg 32 @ y8 [31:0] $end
$var reg 32 A y9 [31:0] $end
$var integer 32 B i [31:0] $end
$upscope $end
$upscope $end
$enddefinitions $end
#0
$dumpvars
bx B
bx A
bx @
bx ?
bx >
bx =
bx <
bx ;
bx :
bx 9
bx 8
bx 7
bx 6
bx 5
bx 4
bx 3
bx 2
b0 1
bx 0
bx /
bx .
bx -
bx ,
b10000000000000000000000000000000 +
x*
bx )
b1111111111111111111111111111111 (
x'
1&
0%
0$
bx #
x"
x!
$end
#5
b0 /
1$
#10
0!
0*
b0 )
b0 5
b0 6
b0 9
b0 A
b0 @
b0 ?
b0 >
b0 =
b0 <
b0 ;
b0 :
b0 8
b0 7
b0 4
b0 -
b0 .
b0 ,
b1001110000 B
0$
0&
#15
b1001110000 B
1$
#20
0$
1&
#25
b10000111100001111000011110000101 )
1$
#30
0$
#35
1$
#40
0$
#45
1$
#50
0$
#55
1$
#60
b1 1
0$
1'
#65
b11010000101000011010010001111010 )
b1 ,
b1 /
1$
#70
0$
#75
b11001000001000010010111000100000 )
b10 ,
1$
#80
0$
0'
#85
b1111001101001100101001010100011 )
b11 ,
1$
#90
0$
#95
b111010011001101010101010010 )
b100 ,
1$
#100
0$
#105
b1101100101101110000101101011111 )
b101 ,
1$
#110
0$
#115
b111100111001100101001110000000 )
b110 ,
1$
#120
0$
#125
b10010010000011100111000110000100 )
b111 ,
1$
#130
0$
#135
b100101000011100110110100011011 )
b1000 ,
1$
#140
0$
#145
b10110110110100010111111010101101 )
b1001 ,
1$
#150
0$
#155
b10110000001011001000111101001000 )
b1010 ,
1$
#160
0$
#165
b10100101001110100000111101110000 )
b1011 ,
1$
#170
0$
#175
b11101110001110110000011100111000 )
b1100 ,
1$
#180
0$
#185
b1100110101011101101000100100101 )
b1101 ,
1$
#190
0$
#195
b1100100111010000101000010100111 )
b1110 ,
1$
#200
0$
#205
b11001011011000100011000011110010 )
b1111 ,
1$
#210
0$
#215
b111000100011001101000110001001 )
b10000 ,
1$
#220
0$
#225
b110010011011111111110000011101 )
b10001 ,
1$
#230
0$
#235
b11110100111001001111110010000001 )
b10010 ,
1$
#240
0$
#245
b1111100111111111010011111110110 )
b10011 ,
1$
#250
0$
#255
b10000001011110011110101000100011 )
b10100 ,
1$
#260
0$
#265
b1111110010110110001101011100010 )
b10101 ,
1$
#270
0$
#275
b10101111100000101000110100111101 )
b10110 ,
1$
#280
0$
#285
b10110100110000100101111000100101 )
b10111 ,
1$
#290
0$
#295
b10000100000100111111000110110010 )
b11000 ,
1$
#300
0$
#305
b1111100000101001001110101010011 )
b11001 ,
1$
#310
0$
#315
b1001101100110000111110011011001 )
b11010 ,
1$
#320
0$
#325
b101101111010000110001010110111 )
b11011 ,
1$
#330
0$
#335
b1100000100000111110000101001111 )
b11100 ,
1$
#340
0$
#345
b100100110001000010101101000111 )
b11101 ,
1$
#350
0$
#355
b10011111011111110001001000100010 )
b11110 ,
1$
#360
0$
#365
b11000100110001000101100110001011 )
b11111 ,
1$
#370
0$
#375
b11001100001011111011011011110101 )
b100000 ,
1$
#380
0$
#385
b1110100011011110100101111001000 )
b100001 ,
1$
#390
0$
#395
b11110001111011101110111000001010 )
b100010 ,
1$
#400
0$
#405
b1010111011010100010000010100 )
b100011 ,
1$
#410
0$
#415
b10010101100101101001000000000101 )
b100100 ,
1$
#420
0$
#425
b10100011100111000111111100011111 )
b100101 ,
1$
#430
0$
#435
b11011010100111101011111001100011 )
b100110 ,
1$
#440
0$
#445
b101101001110010001100000110101 )
b100111 ,
1$
#450
0$
#455
b1101010111011011110101000010001 )
b101000 ,
1$
#460
0$
#465
b10100100101110111000111011101 )
b101001 ,
1$
#470
0$
#475
b10000100101110100011000101011000 )
b101010 ,
1$
#480
0$
#485
b1111011010001011000111111100011 )
b101011 ,
1$
#490
0$
#495
b10001111101001110011111110111000 )
b101100 ,
1$
#500
0$
#505
b10001100000111011001101111000110 )
b101101 ,
1$
#510
0$
#515
b11101010011101010110101101001000 )
b101110 ,
1$
#520
0$
#525
b10100101101101001101101110010100 )
b101111 ,
1$
#530
0$
#535
b10011010111010001101010110010001 )
b110000 ,
1$
#540
0$
#545
b10111011000111011101101101100111 )
b110001 ,
1$
#550
0$
#555
b1000001000000101010111011010101 )
b110010 ,
1$
#560
0$
#565
b10111001011100011111011100111001 )
b110011 ,
1$
#570
0$
#575
b11110101110100110000101010110011 )
b110100 ,
1$
#580
0$
#585
b10111011111000100000001111010001 )
b110101 ,
1$
#590
0$
#595
b1011010111011010101101010101011 )
b110110 ,
1$
#600
0$
#605
b10000011110101110100100010101111 )
b110111 ,
1$
#610
0$
#615
b1010100111100101010001000010 )
b111000 ,
1$
#620
0$
#625
b10001010111001001000001000010 )
b111001 ,
1$
#630
0$
#635
b101100100001100011110001000011 )
b111010 ,
1$
#640
0$
#645
b1010001000010101010000110101000 )
b111011 ,
1$
#650
0$
#655
b11110101010011001010111110000000 )
b111100 ,
1$
#660
0$
#665
b10011101101011001011110110111110 )
b111101 ,
1$
#670
0$
#675
b11111110111000111000101000110000 )
b111110 ,
1$
#680
0$
#685
b1011100000010010011010100101111 )
b111111 ,
1$
#690
0$
#695
b10000101011000010010001011001000 )
b1000000 ,
1$
#700
0$
#705
b11101110011001111100000100101011 )
b1000001 ,
1$
#710
0$
#715
b1011111000011100100111000 )
b1000010 ,
1$
#720
0$
#725
b1000001001010011000101101011011 )
b1000011 ,
1$
#730
0$
#735
b100100011101001010111000101010 )
b1000100 ,
1$
#740
0$
#745
b1001110011000110011000011010111 )
b1000101 ,
1$
#750
0$
#755
b1100001001100101010000011000 )
b1000110 ,
1$
#760
0$
#765
b10111010110010000000010110111100 )
b1000111 ,
1$
#770
0$
#775
b110100000111111101111101110011 )
b1001000 ,
1$
#780
0$
#785
b111111010011001011001110100111 )
b1001001 ,
1$
#790
0$
#795
b1100010111110000100000000101101 )
b1001010 ,
1$
#800
0$
#805
b10100011100001000110011100001001 )
b1001011 ,
1$
#810
0$
#815
b11111011100111110111011111011011 )
b1001100 ,
1$
#820
0$
#825
b1001000000010110111110010110010 )
b1001101 ,
1$
#830
0$
#835
b10011001000010111010010000111 )
b1001110 ,
1$
#840
0$
#845
b10010111010000000011100010010011 )
b1001111 ,
1$
#850
0$
#855
b10011010101000011111110101001100 )
b1010000 ,
1$
#860
0$
#865
b10101111100010101001101101001110 )
b1010001 ,
1$
#870
0$
#875
b10010101111011100000010000010101 )
b1010010 ,
1$
#880
0$
#885
b1111111101010011101100110011010 )
b1010011 ,
1$
#890
0$
#895
b101110101011000100010000010101 )
b1010100 ,
1$
#900
0$
#905
b1010010111110010001100110011100 )
b1010101 ,
1$
#910
0$
#915
b10001110001111111001011011100011 )
b1010110 ,
1$
#920
0$
#925
b1011000010110000001011100101 )
b1010111 ,
1$
#930
0$
#935
b11110000001001111011000110110011 )
b1011000 ,
1$
#940
0$
#945
b1011101101001101110011011110110 )
b1011001 ,
1$
#950
0$
#955
b1011101001011001100010101100110 )
b1011010 ,
1$
#960
0$
#965
b100110000101110111011110011000 )
b1011011 ,
1$
#970
0$
#975
b11111011011010101000011101010000 )
b1011100 ,
1$
#980
0$
#985
b10100110101000010011001011101110 )
b1011101 ,
1$
#990
0$
#995
b11001110010111000111011001000000 )
b1011110 ,
1$
#1000
0$
#1005
b100001100000101110011110011110 )
b1011111 ,
1$
#1010
0$
#1015
b1000011111010101110111110110100 )
b1100000 ,
1$
#1020
0$
#1025
b11111000111110011001100100 )
b1100001 ,
1$
#1030
0$
#1035
b11111011111100010110100111010110 )
b1100010 ,
1$
#1040
0$
#1045
b11000100101111000100011111010011 )
b1100011 ,
1$
#1050
0$
#1055
b1011011011111010100000110100011 )
b1100100 ,
1$
#1060
0$
#1065
b10110000000000000010000010110001 )
b1100101 ,
1$
#1070
0$
#1075
b10010011000101001111100111010 )
b1100110 ,
1$
#1080
0$
#1085
b11011010101101001101110001001011 )
b1100111 ,
1$
#1090
0$
#1095
b10111101010011000000110011111100 )
b1101000 ,
1$
#1100
0$
#1105
b1100110101111111101111010100 )
b1101001 ,
1$
#1110
0$
#1115
b11111001110001101100111100001110 )
b1101010 ,
1$
#1120
0$
#1125
b10000001101000000010111011110010 )
b1101011 ,
1$
#1130
0$
#1135
b111101111100000000011111100101 )
b1101100 ,
1$
#1140
0$
#1145
b10110111001011111010101011000111 )
b1101101 ,
1$
#1150
0$
#1155
b1100111101000111101111111110001 )
b1101110 ,
1$
#1160
0$
#1165
b1100010000101100101001110000010 )
b1101111 ,
1$
#1170
0$
#1175
b11000110000011011000010010111010 )
b1110000 ,
1$
#1180
0$
#1185
b1111000011100101110011111010011 )
b1110001 ,
1$
#1190
0$
#1195
b1011110001010100110000110110001 )
b1110010 ,
1$
#1200
0$
#1205
b101100110101110100010001000111 )
b1110011 ,
1$
#1210
0$
#1215
b10110110011010001110111101110100 )
b1110100 ,
1$
#1220
0$
#1225
b10011011101101111000110100111010 )
b1110101 ,
1$
#1230
0$
#1235
b11111110100101001100001001010100 )
b1110110 ,
1$
#1240
0$
#1245
b11001100111110111001111110011001 )
b1110111 ,
1$
#1250
0$
#1255
b1110000110111011101100011010101 )
b1111000 ,
1$
#1260
0$
#1265
b1010011000111000100110000001 )
b1111001 ,
1$
#1270
0$
#1275
b10001100011000100100100101011100 )
b1111010 ,
1$
#1280
0$
#1285
b11001101100011010010110111000101 )
b1111011 ,
1$
#1290
0$
#1295
b10100101000111110000110100 )
b1111100 ,
1$
#1300
0$
#1305
b11010000011110001101010100000011 )
b1111101 ,
1$
#1310
0$
#1315
b101111111010010110101100 )
b1111110 ,
1$
#1320
0$
#1325
b11110010111110010110100101011001 )
b1111111 ,
1$
#1330
0$
#1335
b11000011001101100011000110011111 )
b10000000 ,
1$
#1340
0$
#1345
b1110100010010001010101100111010 )
b10000001 ,
1$
#1350
0$
#1355
b11101010111000111001100001100000 )
b10000010 ,
1$
#1360
0$
#1365
b100010111101100111111001100010 )
b10000011 ,
1$
#1370
0$
#1375
b10000001100100000100111100101111 )
b10000100 ,
1$
#1380
0$
#1385
b1010110100110000110010100001110 )
b10000101 ,
1$
#1390
0$
#1395
b1100011100101100101110100001010 )
b10000110 ,
1$
#1400
0$
#1405
b10000101011000110000111101111010 )
b10000111 ,
1$
#1410
0$
#1415
b10000111101100110110010110101011 )
b10001000 ,
1$
#1420
0$
#1425
b1110110110111001001111111111110 )
b10001001 ,
1$
#1430
0$
#1435
b1111110100111000000110110111110 )
b10001010 ,
1$
#1440
0$
#1445
b11111111000111100001101010000011 )
b10001011 ,
1$
#1450
0$
#1455
b11000000101001011001000100111001 )
b10001100 ,
1$
#1460
0$
#1465
b10100000100110001100110100001011 )
b10001101 ,
1$
#1470
0$
#1475
b1100001010100001100100011100101 )
b10001110 ,
1$
#1480
0$
#1485
b10111010101001001100111111100101 )
b10001111 ,
1$
#1490
0$
#1495
b100001100010101001001011101000 )
b10010000 ,
1$
#1500
0$
#1505
b1001000101000100001111000011001 )
b10010001 ,
1$
#1510
0$
#1515
b11001000110000000100000101101101 )
b10010010 ,
1$
#1520
0$
#1525
b11011100110110000010010110010000 )
b10010011 ,
1$
#1530
0$
#1535
b10010100010100001110001001100001 )
b10010100 ,
1$
#1540
0$
#1545
b11101001101101100011100111011010 )
b10010101 ,
1$
#1550
0$
#1555
b1000110110100000111110110010110 )
b10010110 ,
1$
#1560
0$
#1565
b111010100100001101001011000100 )
b10010111 ,
1$
#1570
0$
#1575
b1111010010100000101111101011 )
b10011000 ,
1$
#1580
0$
#1585
b100000000001000111011101001111 )
b10011001 ,
1$
#1590
0$
#1595
b10011100110001010101100111000110 )
b10011010 ,
1$
#1600
0$
#1605
b1110011010100010110000110111001 )
b10011011 ,
1$
#1610
0$
#1615
b11000100011101101000111110011011 )
b10011100 ,
1$
#1620
0$
#1625
b1000110110111011001101111000010 )
b10011101 ,
1$
#1630
0$
#1635
b10101000000101110100011000100101 )
b10011110 ,
1$
#1640
0$
#1645
b1001100101110110111101000110110 )
b10011111 ,
1$
#1650
0$
#1655
b10111001110110000001110111101111 )
b10100000 ,
1$
#1660
0$
#1665
b10011111110100011011011011101001 )
b10100001 ,
1$
#1670
0$
#1675
b10010100111111101101101110001100 )
b10100010 ,
1$
#1680
0$
#1685
b111100110111101000101011011110 )
b10100011 ,
1$
#1690
0$
#1695
b10010000001011111001100000111011 )
b10100100 ,
1$
#1700
0$
#1705
b1101000110110111010001011101010 )
b10100101 ,
1$
#1710
0$
#1715
b10101001111001000000011110111 )
b10100110 ,
1$
#1720
0$
#1725
b1111100101001000001000100011000 )
b10100111 ,
1$
#1730
0$
#1735
b10010001100010001001011100011101 )
b10101000 ,
1$
#1740
0$
#1745
b11100001100011010010010000011010 )
b10101001 ,
1$
#1750
0$
#1755
b1111001101101110010100011101010 )
b10101010 ,
1$
#1760
0$
#1765
b11100000100011100101111011111111 )
b10101011 ,
1$
#1770
0$
#1775
b11110101111110101111001001000101 )
b10101100 ,
1$
#1780
0$
#1785
b10011100010111000001011100101 )
b10101101 ,
1$
#1790
0$
#1795
b10001111010110100011001000000100 )
b10101110 ,
1$
#1800
0$
#1805
b11100001011101011110000001000001 )
b10101111 ,
1$
#1810
0$
#1815
b10010110010010110100001101010110 )
b10110000 ,
1$
#1820
0$
#1825
b10110010000101001001011110011100 )
b10110001 ,
1$
#1830
0$
#1835
b111100100001100100110100111101 )
b10110010 ,
1$
#1840
0$
#1845
b10011000111111010001111011000001 )
b10110011 ,
1$
#1850
0$
#1855
b10100100110010110101111011000 )
b10110100 ,
1$
#1860
0$
#1865
b1001110001001100010010011101101 )
b10110101 ,
1$
#1870
0$
#1875
b111101010010100110011100110110 )
b10110110 ,
1$
#1880
0$
#1885
b10011010000100001001111100000110 )
b10110111 ,
1$
#1890
0$
#1895
b10001110110100101111010000010111 )
b10111000 ,
1$
#1900
0$
#1905
b10011110011110111001110011001001 )
b10111001 ,
1$
#1910
0$
#1915
b11000011001010110110110100000101 )
b10111010 ,
1$
#1920
0$
#1925
b1010100100111001011000010110010 )
b10111011 ,
1$
#1930
0$
#1935
b101001001111101111100011110101 )
b10111100 ,
1$
#1940
0$
#1945
b100011110001100101011001100101 )
b10111101 ,
1$
#1950
0$
#1955
b111010001111110010001110010110 )
b10111110 ,
1$
#1960
0$
#1965
b110000011100101000011101100 )
b10111111 ,
1$
#1970
0$
#1975
b11010011011010000011100111011000 )
b11000000 ,
1$
#1980
0$
#1985
b11100011111110110110101011111011 )
b11000001 ,
1$
#1990
0$
#1995
b1001111010011101000100011001001 )
b11000010 ,
1$
#2000
0$
#2005
b11011010101011101000100100001100 )
b11000011 ,
1$
#2010
0$
#2015
b1111101100001110111111001111110 )
b11000100 ,
1$
#2020
0$
#2025
b10100110100110000101011001111000 )
b11000101 ,
1$
#2030
0$
#2035
b111101101010000101011000011101 )
b11000110 ,
1$
#2040
0$
#2045
b10010100111111100110111 )
b11000111 ,
1$
#2050
0$
#2055
b10101001111110011010000001111000 )
b11001000 ,
1$
#2060
0$
#2065
b10101001101001001000100000100010 )
b11001001 ,
1$
#2070
0$
#2075
b1011101100011110100000110011 )
b11001010 ,
1$
#2080
0$
#2085
b10101111110110001110011111101011 )
b11001011 ,
1$
#2090
0$
#2095
b11110000000111010100001110000001 )
b11001100 ,
1$
#2100
0$
#2105
b10101001001100101010101110110011 )
b11001101 ,
1$
#2110
0$
#2115
b10100110001011000100101101100 )
b11001110 ,
1$
#2120
0$
#2125
b111010011011100000010001101010 )
b11001111 ,
1$
#2130
0$
#2135
b11000100101010100111100010100010 )
b11010000 ,
1$
#2140
0$
#2145
b1110110001111100100101010111011 )
b11010001 ,
1$
#2150
0$
#2155
b11101011101011101000111110011011 )
b11010010 ,
1$
#2160
0$
#2165
b10110111111101011001101111111011 )
b11010011 ,
1$
#2170
0$
#2175
b101100001111001101110111011010 )
b11010100 ,
1$
#2180
0$
#2185
b1111101100110011000111010110 )
b11010101 ,
1$
#2190
0$
#2195
b10111100001110000011000001000001 )
b11010110 ,
1$
#2200
0$
#2205
b10001110001001101001101111011 )
b11010111 ,
1$
#2210
0$
#2215
b100001100010100001101011110 )
b11011000 ,
1$
#2220
0$
#2225
b10000100000011101110001011101100 )
b11011001 ,
1$
#2230
0$
#2235
b11010101110000111101001111110110 )
b11011010 ,
1$
#2240
0$
#2245
b10110110011010110100011011101010 )
b11011011 ,
1$
#2250
0$
#2255
b1001101011000011010100101101 )
b11011100 ,
1$
#2260
0$
#2265
b1101001101000010001000010011100 )
b11011101 ,
1$
#2270
0$
#2275
b100010101100110000101001101001 )
b11011110 ,
1$
#2280
0$
#2285
b10110000101000100110101001011 )
b11011111 ,
1$
#2290
0$
#2295
b1010100011011001010001001110111 )
b11100000 ,
1$
#2300
0$
#2305
b10111000011101100100011010011 )
b11100001 ,
1$
#2310
0$
#2315
b10000100000100110010011100100010 )
b11100010 ,
1$
#2320
0$
#2325
b11000101011011011010001101001111 )
b11100011 ,
1$
#2330
0$
#2335
b1011011110011111011011000001111 )
b11100100 ,
1$
#2340
0$
#2345
b10101111110010011101101111001101 )
b11100101 ,
1$
#2350
0$
#2355
b11011111110111110110110111000101 )
b11100110 ,
1$
#2360
0$
#2365
b1010001111011110010011111 )
b11100111 ,
1$
#2370
0$
#2375
b100001100101111000001010100010 )
b11101000 ,
1$
#2380
0$
#2385
b1000000000111010011110011010011 )
b11101001 ,
1$
#2390
0$
#2395
b10011110110110101110101100101010 )
b11101010 ,
1$
#2400
0$
#2405
b11111010010111100100001001111111 )
b11101011 ,
1$
#2410
0$
#2415
b10011110001111110011010000000100 )
b11101100 ,
1$
#2420
0$
#2425
b1011101111000011010101010000001 )
b11101101 ,
1$
#2430
0$
#2435
b11100011110011100100111011010001 )
b11101110 ,
1$
#2440
0$
#2445
b10011100010010011111001001100001 )
b11101111 ,
1$
#2450
0$
#2455
b11001000100010011000101000110111 )
b11110000 ,
1$
#2460
0$
#2465
b10110100101110111111011110100001 )
b11110001 ,
1$
#2470
0$
#2475
b10010111000101001101110001110100 )
b11110010 ,
1$
#2480
0$
#2485
b10111100011000010000111010110100 )
b11110011 ,
1$
#2490
0$
#2495
b10011010000101010010000111110101 )
b11110100 ,
1$
#2500
0$
#2505
b1100011001101011000001110011100 )
b11110101 ,
1$
#2510
0$
#2515
b110000110011110110100110000001 )
b11110110 ,
1$
#2520
0$
#2525
b10001111110100011010100111011001 )
b11110111 ,
1$
#2530
0$
#2535
b100010100011000010010010010100 )
b11111000 ,
1$
#2540
0$
#2545
b10000111010011010001101011100 )
b11111001 ,
1$
#2550
0$
#2555
b11111100000111011011000001000110 )
b11111010 ,
1$
#2560
0$
#2565
b10110100111101100000001010011010 )
b11111011 ,
1$
#2570
0$
#2575
b10110101010010111000110111101 )
b11111100 ,
1$
#2580
0$
#2585
b1110110111000110000010110001100 )
b11111101 ,
1$
#2590
0$
#2595
b10011100010111010001110100111011 )
b11111110 ,
1$
#2600
0$
#2605
b110101111111100001110001000101 )
b11111111 ,
1$
#2610
0$
#2615
b101100010001010001010100111000 )
b100000000 ,
1$
#2620
0$
#2625
b10100100001001000101100000011010 )
b100000001 ,
1$
#2630
0$
#2635
b10010110001100101010110101000001 )
b100000010 ,
1$
#2640
0$
#2645
b10001001011111010010010010100101 )
b100000011 ,
1$
#2650
0$
#2655
b11010011011111101100001100011111 )
b100000100 ,
1$
#2660
0$
#2665
b10110001010001111001001100111101 )
b100000101 ,
1$
#2670
0$
#2675
b1101100111011110100010110 )
b100000110 ,
1$
#2680
0$
#2685
b1001111101101000110000010110101 )
b100000111 ,
1$
#2690
0$
#2695
b11111010110111100000010101110011 )
b100001000 ,
1$
#2700
0$
#2705
b1110100101001111011001001100110 )
b100001001 ,
1$
#2710
0$
#2715
b10101101011010111111100101000101 )
b100001010 ,
1$
#2720
0$
#2725
b100000111000100100011001000011 )
b100001011 ,
1$
#2730
0$
#2735
b1000000101101001001010001111011 )
b100001100 ,
1$
#2740
0$
#2745
b11110000100010110100010010011 )
b100001101 ,
1$
#2750
0$
#2755
b1101110110011110111000001100 )
b100001110 ,
1$
#2760
0$
#2765
b10101001101100110101011111001000 )
b100001111 ,
1$
#2770
0$
#2775
b10110100001100111010101011110101 )
b100010000 ,
1$
#2780
0$
#2785
b11000111100100101001000010111010 )
b100010001 ,
1$
#2790
0$
#2795
b10011001010111001010010001110001 )
b100010010 ,
1$
#2800
0$
#2805
b1000000101001000101101010100110 )
b100010011 ,
1$
#2810
0$
#2815
b11110111111001001001101010010010 )
b100010100 ,
1$
#2820
0$
#2825
b11110101111001110001111010101101 )
b100010101 ,
1$
#2830
0$
#2835
b10000110010101001011000001010100 )
b100010110 ,
1$
#2840
0$
#2845
b10010100000100101000011000111000 )
b100010111 ,
1$
#2850
0$
#2855
b10100000101010101110110100101101 )
b100011000 ,
1$
#2860
0$
#2865
b1010100100101111010100011011000 )
b100011001 ,
1$
#2870
0$
#2875
b1000111000110010011011001010000 )
b100011010 ,
1$
#2880
0$
#2885
b11000111001100110011111010101001 )
b100011011 ,
1$
#2890
0$
#2895
b110010111110010101011001000 )
b100011100 ,
1$
#2900
0$
#2905
b11111100111010001110101000000111 )
b100011101 ,
1$
#2910
0$
#2915
b11000111010100110001010011100011 )
b100011110 ,
1$
#2920
0$
#2925
b1110000001010011011100110101100 )
b100011111 ,
1$
#2930
0$
#2935
b111000100001110100110111111011 )
b100100000 ,
1$
#2940
0$
#2945
b10111011111110100001100000100101 )
b100100001 ,
1$
#2950
0$
#2955
b1000101100110100101010010111011 )
b100100010 ,
1$
#2960
0$
#2965
b1000010010110001000000111101000 )
b100100011 ,
1$
#2970
0$
#2975
b11110111110010000110100110101000 )
b100100100 ,
1$
#2980
0$
#2985
b11000110001101001001100001101111 )
b100100101 ,
1$
#2990
0$
#2995
b1010111010111001000101111110001 )
b100100110 ,
1$
#3000
0$
#3005
b1111101111111100011000000111010 )
b100100111 ,
1$
#3010
0$
#3015
b10000110101011100001001000001011 )
b100101000 ,
1$
#3020
0$
#3025
b1101100101000100000001001111110 )
b100101001 ,
1$
#3030
0$
#3035
b11001000101100100110101011011100 )
b100101010 ,
1$
#3040
0$
#3045
b1100101100101111110010111110111 )
b100101011 ,
1$
#3050
0$
#3055
b11011100101111111110101010011101 )
b100101100 ,
1$
#3060
0$
#3065
b1110010100100001001011000011100 )
b100101101 ,
1$
#3070
0$
#3075
b1111110001001000011011000111000 )
b100101110 ,
1$
#3080
0$
#3085
b1000000110101010101110101000111 )
b100101111 ,
1$
#3090
0$
#3095
b1000100000010011100110100110011 )
b100110000 ,
1$
#3100
0$
#3105
b110111000100110100000101001111 )
b100110001 ,
1$
#3110
0$
#3115
b100101101101010000110001011100 )
b100110010 ,
1$
#3120
0$
